tpds_extension/keystream_connect/extension.yaml
tpds_extension/keystream_connect/setup.py
tpds_extension/keystream_connect/version.py
tpds_extension/keystream_connect/TrustManaged/firmware.zip
tpds_extension/keystream_connect/TrustManaged/keySTREAM AWS Connect-TMG.ipynb
tpds_extension/keystream_connect/TrustManaged/assets/aws-zero-touch-full-setup-cn.yaml
tpds_extension/keystream_connect/TrustManaged/assets/aws-zero-touch-full-setup.yaml
tpds_extension/keystream_connect/TrustManaged/assets/aws_credentials.yaml
tpds_extension/keystream_connect/TrustManaged/assets/keySTREAM AWS Connect.md
tpds_extension/keystream_connect/TrustManaged/assets/keystream_config.yaml
tpds_extension/keystream_connect/TrustManaged/assets/images/2_tier_device_profile_list_tpds.png
tpds_extension/keystream_connect/TrustManaged/assets/images/2_tier_profile_details.png
tpds_extension/keystream_connect/TrustManaged/assets/images/2tier_ca.png
tpds_extension/keystream_connect/TrustManaged/assets/images/2tier_create.png
tpds_extension/keystream_connect/TrustManaged/assets/images/2tier_fleet.png
tpds_extension/keystream_connect/TrustManaged/assets/images/2tier_pop.png
tpds_extension/keystream_connect/TrustManaged/assets/images/ATSAME54-XPRO.png
tpds_extension/keystream_connect/TrustManaged/assets/images/Activated_Message.png
tpds_extension/keystream_connect/TrustManaged/assets/images/Aws_failed.png
tpds_extension/keystream_connect/TrustManaged/assets/images/DM320118_WINC.png
tpds_extension/keystream_connect/TrustManaged/assets/images/Drop_Down.png
tpds_extension/keystream_connect/TrustManaged/assets/images/Edit_configuration.png
tpds_extension/keystream_connect/TrustManaged/assets/images/Email.png
tpds_extension/keystream_connect/TrustManaged/assets/images/Files_properties.png
tpds_extension/keystream_connect/TrustManaged/assets/images/Iam_dashboard.png
tpds_extension/keystream_connect/TrustManaged/assets/images/KS_AWS_Usecase_Steps.png
tpds_extension_keystream_connect-1.3.0.dist-info/licenses/LICENSE
tpds_extension_keystream_connect-1.3.0.dist-info/METADATA
tpds_extension_keystream_connect-1.3.0.dist-info/WHEEL
tpds_extension_keystream_connect-1.3.0.dist-info/top_level.txt
tpds_extension_keystream_connect-1.3.0.dist-info/RECORD
